sanddance/__init__.py
sanddance/example.py
sanddance/frontend/build/asset-manifest.json
sanddance/frontend/build/index.html
sanddance/frontend/build/static/css/main.22971256.css
sanddance/frontend/build/static/css/main.22971256.css.map
sanddance/frontend/build/static/js/main.f0f7d94c.js
sanddance/frontend/build/static/js/main.f0f7d94c.js.LICENSE.txt
sanddance/frontend/build/static/js/main.f0f7d94c.js.map
streamlit-sanddance/__init__.py
streamlit-sanddance/example.py
streamlit-sanddance/types_explorer.py
streamlit-sanddance/types_insight.py
streamlit_sanddance/__init__.py
streamlit_sanddance/example.py
streamlit_sanddance/types_explorer.py
streamlit_sanddance/types_insight.py
streamlit_sanddance/frontend/build/asset-manifest.json
streamlit_sanddance/frontend/build/index.html
streamlit_sanddance/frontend/build/static/css/main.22971256.css
streamlit_sanddance/frontend/build/static/css/main.22971256.css.map
streamlit_sanddance/frontend/build/static/js/main.6786ce3e.js
streamlit_sanddance/frontend/build/static/js/main.6786ce3e.js.LICENSE.txt
streamlit_sanddance/frontend/build/static/js/main.6786ce3e.js.map
streamlit_sanddance/frontend/build/static/js/main.f0f7d94c.js
streamlit_sanddance/frontend/build/static/js/main.f0f7d94c.js.LICENSE.txt
streamlit_sanddance/frontend/build/static/js/main.f0f7d94c.js.map
streamlit_sanddance/frontend/build/static/js/main.f134b29e.js
streamlit_sanddance/frontend/build/static/js/main.f134b29e.js.LICENSE.txt
streamlit_sanddance/frontend/build/static/js/main.f134b29e.js.map
streamlit_sanddance-0.0.7.dist-info/LICENSE
streamlit_sanddance-0.0.7.dist-info/METADATA
streamlit_sanddance-0.0.7.dist-info/WHEEL
streamlit_sanddance-0.0.7.dist-info/top_level.txt
streamlit_sanddance-0.0.7.dist-info/RECORD
