Metadata-Version: 2.1
Name: streamlit-sanddance
Version: 0.0.7
Summary: Streamlit component that allows you to view a SandDance visualization of a dataframe.
Home-page: https://microsoft.github.io/SandDance
Author: Dan Marshall
Author-email: danmar@microsoft.com
Requires-Python: >=3.7
License-File: LICENSE
Requires-Dist: streamlit >=0.63
Provides-Extra: devel
Requires-Dist: wheel ; extra == 'devel'
Requires-Dist: pytest ==7.4.0 ; extra == 'devel'
Requires-Dist: playwright ==1.36.0 ; extra == 'devel'
Requires-Dist: requests ==2.31.0 ; extra == 'devel'
Requires-Dist: pytest-playwright-snapshot ==1.0 ; extra == 'devel'
Requires-Dist: pytest-rerunfailures ==12.0 ; extra == 'devel'
